README.md
setup.cfg
setup.py
vvm_lib/__init__.py
vvm_lib/google_book.py
vvm_lib/greenplum.py
vvm_lib/mssql.py
vvm_lib/vault.py
vvm_lib.egg-info/PKG-INFO
vvm_lib.egg-info/SOURCES.txt
vvm_lib.egg-info/dependency_links.txt
vvm_lib.egg-info/not-zip-safe
vvm_lib.egg-info/top_level.txt
vvm_lib/db/__init__.py
vvm_lib/db/db.py