Metadata-Version: 2.1
Name: vvm_lib
Version: 1.0.7
Summary: my frequently used functions
Home-page: https://github.com/VazhikVM/vvm_lib
Author: vvazhinskiy
Author-email: v.vazhinskiy@yandex.ru
